{
  "version": 1,
  "last_updated": "2026-01-09T03:10:40.863009+00:00",
  "by_type": {
    "Person": {
      "bo nix": "bo-nix",
      "riley moss": "riley-moss",
      "mike mcglinchey": "mike-mcglinchey",
      "marvin mims jr.": "marvin-mims-jr",
      "rj harvey": "rj-harvey",
      "zach allen": "zach-allen",
      "adam trautman": "adam-trautman",
      "nate adkins": "nate-adkins",
      "brandon jones": "brandon-jones",
      "d.j. jones": "d-j-jones",
      "ja'quan mcmillian": "ja-quan-mcmillian",
      "jonah elliss": "jonah-elliss",
      "jorge tinajero": "jorge-tinajero",
      "ricardo saucedo": "ricardo-saucedo",
      "joe lombardi": "joe-lombardi",
      "vance joseph": "vance-joseph",
      "darren rizzi": "darren-rizzi",
      "sean payton": "sean-payton",
      "pat bryant": "pat-bryant",
      "malcolm roach": "malcolm-roach",
      "frank crum": "frank-crum",
      "que robinson": "que-robinson",
      "montee ball": "montee-ball",
      "reuben droughns": "reuben-droughns",
      "julia": "julia",
      "sydney j": "sydney-j",
      "alex singleton": "alex-singleton",
      "pat surtain": "pat-surtain",
      "trey lance": "trey-lance",
      "elisa hernandez": "elisa-hernandez",
      "aric dilalla": "aric-dilalla",
      "courtland sutton": "courtland-sutton",
      "jim nantz": "jim-nantz",
      "tony romo": "tony-romo",
      "tracy wolfson": "tracy-wolfson",
      "dave logan": "dave-logan",
      "rick lewis": "rick-lewis",
      "susie wargin": "susie-wargin",
      "larry kahn": "larry-kahn",
      "marvin lewis": "marvin-lewis",
      "karene reid": "karene-reid",
      "ben powers": "ben-powers",
      "john franklin-myers": "john-franklin-myers",
      "dre greenlaw": "dre-greenlaw"
    },
    "Organization": {},
    "Concept": {}
  }
}